pbake/__init__.py
pbake/bake.py
pbake/cookbook.py
pbake/shell.py
pbake-0.0.6.dist-info/METADATA
pbake-0.0.6.dist-info/WHEEL
pbake-0.0.6.dist-info/entry_points.txt
pbake-0.0.6.dist-info/licenses/LICENSE
pbake-0.0.6.dist-info/RECORD
